shellpad/__init__.py
shellpad/main.py
shellpad-1.1.dist-info/licenses/LICENSE
shellpad-1.1.dist-info/METADATA
shellpad-1.1.dist-info/WHEEL
shellpad-1.1.dist-info/entry_points.txt
shellpad-1.1.dist-info/top_level.txt
shellpad-1.1.dist-info/RECORD
