Metadata-Version: 2.4
Name: shellpad
Version: 1.1
Summary: A minimalist notebook for your shell.
Author: wormcracker
License: MIT
Keywords: terminal,notes,markdown,cli,tui
Requires-Python: >=3.8
License-File: LICENSE
Provides-Extra: windows
Requires-Dist: windows-curses; extra == "windows"
Dynamic: license-file
